metric_learning_layers/__init__.py
metric_learning_layers/mml.py
metric_learning_layers/utils.py
Metric_Learning_Layers-0.1.6.dist-info/LICENSE
Metric_Learning_Layers-0.1.6.dist-info/METADATA
Metric_Learning_Layers-0.1.6.dist-info/WHEEL
Metric_Learning_Layers-0.1.6.dist-info/top_level.txt
Metric_Learning_Layers-0.1.6.dist-info/RECORD
