Metadata-Version: 2.1
Name: Metric-Learning-Layers
Version: 0.1.6
Summary: A simple PyTorch package that includes the most common metric learning layers.
Home-page: https://github.com/romue404/metric_learning_layers
Author: Robert Müller
Author-email: robert.mueller1990@googlemail.com
License: MIT
Keywords: metric learning,artificial intelligence,pytorch,classification,separability,large margin
Classifier: Development Status :: 4 - Beta
Classifier: Intended Audience :: Developers
Classifier: Topic :: Scientific/Engineering :: Artificial Intelligence
Classifier: License :: OSI Approved :: MIT License
Classifier: Programming Language :: Python :: 3.6
License-File: LICENSE
Requires-Dist: torch (>=1.6)
